jinja2_dev_server/__init__.py
jinja2_dev_server/command_line.py
jinja2_dev_server/server.py
jinja2_dev_server-0.0.5.dist-info/METADATA
jinja2_dev_server-0.0.5.dist-info/RECORD
jinja2_dev_server-0.0.5.dist-info/WHEEL
jinja2_dev_server-0.0.5.dist-info/entry_points.txt
jinja2_dev_server-0.0.5.dist-info/top_level.txt
